domain_event_broker/__init__.py
domain_event_broker/_version.py
domain_event_broker/events.py
domain_event_broker/py.typed
domain_event_broker/replay.py
domain_event_broker/settings.py
domain_event_broker/transport.py
domain_event_broker/django/__init__.py
domain_event_broker/django/apps.py
domain_event_broker/django/transaction.py
domain_event_broker/django/management/__init__.py
domain_event_broker/django/management/commands/__init__.py
domain_event_broker/django/management/commands/replay_domain_event.py
domain_event_broker/tests/__init__.py
domain_event_broker/tests/conftest.py
domain_event_broker/tests/helpers.py
domain_event_broker/tests/test_events.py
domain_event_broker/tests/test_publish.py
domain_event_broker/tests/test_queues.py
domain_event_broker/tests/test_replay.py
domain_event_broker/tests/test_subscriber.py
domain_event_broker/tests/django/__init__.py
domain_event_broker/tests/django/test_publish_on_commit.py
domain_event_broker/tests/django/test_replay_command.py
domain_event_broker/tests/django/test_settings.py
domain_event_broker-3.0.2.dist-info/LICENSE
domain_event_broker-3.0.2.dist-info/METADATA
domain_event_broker-3.0.2.dist-info/WHEEL
domain_event_broker-3.0.2.dist-info/top_level.txt
domain_event_broker-3.0.2.dist-info/RECORD
