Metadata-Version: 2.1
Name: domain-event-broker
Version: 3.0.2
Summary: Send and receive domain events via RabbitMQ
Home-page: https://github.com/AbletonAG/domain-event-broker
Author: Ableton AG
Author-email: webteam@ableton.com
License: MIT
Platform: UNKNOWN
Classifier: Development Status :: 4 - Beta
Classifier: Intended Audience :: Developers
Classifier: Topic :: Software Development :: Libraries :: Python Modules
Classifier: License :: OSI Approved :: MIT License
Classifier: Programming Language :: Python :: 3
Classifier: Programming Language :: Python :: 3.6
Classifier: Programming Language :: Python :: 3.7
Classifier: Programming Language :: Python :: 3.8
Classifier: Programming Language :: Python :: 3.9
Requires-Dist: pika (>=1.2.0)
